cli.py
csvpivot.py
tests.py
csvpivot-1.4.dist-info/METADATA
csvpivot-1.4.dist-info/RECORD
csvpivot-1.4.dist-info/WHEEL
csvpivot-1.4.dist-info/entry_points.txt
csvpivot-1.4.dist-info/top_level.txt
